[
  {
    "env": "prod",
    "severity_scope": "all",
    "start_ms": 2010517003635,
    "end_ms": 2010517003682
  },
  {
    "env": "dmz",
    "severity_scope": "all",
    "start_ms": 2010517201179,
    "end_ms": 2010517201232
  },
  {
    "env": "edge",
    "severity_scope": "all",
    "start_ms": 2010517401218,
    "end_ms": 2010517401265
  },
  {
    "env": "edge",
    "severity_scope": "all",
    "start_ms": 2010517403735,
    "end_ms": 2010517403788
  },
  {
    "env": "core",
    "severity_scope": "all",
    "start_ms": 2010517801153,
    "end_ms": 2010517801200
  },
  {
    "env": "core",
    "severity_scope": "all",
    "start_ms": 2010517802935,
    "end_ms": 2010517802988
  },
  {
    "env": "dns",
    "severity_scope": "all",
    "start_ms": 2010518004043,
    "end_ms": 2010518004090
  },
  {
    "env": "zone",
    "severity_scope": "all",
    "start_ms": 2010518202261,
    "end_ms": 2010518202314
  },
  {
    "env": "core",
    "severity_scope": "all",
    "start_ms": 2010517800053,
    "end_ms": 2010517800147
  },
  {
    "env": "core",
    "severity_scope": "all",
    "start_ms": 2010517801953,
    "end_ms": 2010517802047
  },
  {
    "env": "core",
    "severity_scope": "all",
    "start_ms": 2010517803753,
    "end_ms": 2010517803847
  },
  {
    "env": "dmz",
    "severity_scope": "all",
    "start_ms": 2010517202053,
    "end_ms": 2010517202147
  },
  {
    "env": "dmz",
    "severity_scope": "all",
    "start_ms": 2010517203253,
    "end_ms": 2010517203347
  },
  {
    "env": "dmz",
    "severity_scope": "all",
    "start_ms": 2010517204253,
    "end_ms": 2010517204347
  },
  {
    "env": "dns",
    "severity_scope": "all",
    "start_ms": 2010517810053,
    "end_ms": 2010517810147
  },
  {
    "env": "dns",
    "severity_scope": "all",
    "start_ms": 2010518001053,
    "end_ms": 2010518001147
  },
  {
    "env": "dns",
    "severity_scope": "all",
    "start_ms": 2010518002353,
    "end_ms": 2010518002447
  },
  {
    "env": "edge",
    "severity_scope": "all",
    "start_ms": 2010517402453,
    "end_ms": 2010517402547
  },
  {
    "env": "mesh",
    "severity_scope": "all",
    "start_ms": 2010518401053,
    "end_ms": 2010518401147
  },
  {
    "env": "core",
    "severity_scope": "all",
    "start_ms": 2010517804986,
    "end_ms": 2010517805086
  },
  {
    "env": "dmz",
    "severity_scope": "all",
    "start_ms": 2010517205484,
    "end_ms": 2010517205584
  },
  {
    "env": "dns",
    "severity_scope": "all",
    "start_ms": 2010518005224,
    "end_ms": 2010518005324
  },
  {
    "env": "edge",
    "severity_scope": "all",
    "start_ms": 2010517404908,
    "end_ms": 2010517405008
  },
  {
    "env": "mesh",
    "severity_scope": "all",
    "start_ms": 2010518403714,
    "end_ms": 2010518403814
  },
  {
    "env": "prod",
    "severity_scope": "all",
    "start_ms": 2010517006513,
    "end_ms": 2010517006613
  },
  {
    "env": "vault",
    "severity_scope": "all",
    "start_ms": 2010517605156,
    "end_ms": 2010517605256
  },
  {
    "env": "zone",
    "severity_scope": "all",
    "start_ms": 2010518204597,
    "end_ms": 2010518204697
  },
  {
    "env": "core",
    "severity_scope": "all",
    "start_ms": 2010517807632,
    "end_ms": 2010517807737
  },
  {
    "env": "dmz",
    "severity_scope": "all",
    "start_ms": 2010517208130,
    "end_ms": 2010517208235
  },
  {
    "env": "dns",
    "severity_scope": "all",
    "start_ms": 2010518007870,
    "end_ms": 2010518007975
  },
  {
    "env": "edge",
    "severity_scope": "all",
    "start_ms": 2010517407554,
    "end_ms": 2010517407659
  },
  {
    "env": "mesh",
    "severity_scope": "all",
    "start_ms": 2010518406360,
    "end_ms": 2010518406465
  },
  {
    "env": "prod",
    "severity_scope": "all",
    "start_ms": 2010517009159,
    "end_ms": 2010517009264
  },
  {
    "env": "vault",
    "severity_scope": "all",
    "start_ms": 2010517607802,
    "end_ms": 2010517607907
  },
  {
    "env": "zone",
    "severity_scope": "all",
    "start_ms": 2010518207243,
    "end_ms": 2010518207348
  }
]
